postmail.py
postmail-0.3.dist-info/DESCRIPTION.rst
postmail-0.3.dist-info/METADATA
postmail-0.3.dist-info/RECORD
postmail-0.3.dist-info/WHEEL
postmail-0.3.dist-info/metadata.json
postmail-0.3.dist-info/top_level.txt
